{"is_source_file": true, "format": "TypeScript/TSX (React)", "description": "This file defines a React functional component named SetupPage that renders a multi-section configuration page for setting up business details, keywords, and platform monitoring options in a web application. It includes form elements, layout, and styling for user interaction and configuration management.", "external_files": ["react"], "external_methods": [], "published": ["SetupPage"], "classes": [], "methods": [{"name": "SetupPage", "description": "React component rendering the setup/configuration page for the application."}], "calls": ["React"], "search-terms": ["SetupPage", "configuration", "business category", "keywords", "platform settings", "react functional component", "tsx"], "state": 2, "file_id": 16, "knowledge_revision": 46, "git_revision": "", "ctags": [], "hash": "e57ba93c85a14f21c457be9c4ebc2d52", "format-version": 4, "code-base-name": "trendscout_frontend", "filename": "trendscout_frontend/src/app/(dashboard)/setup/page.tsx", "revision_history": [{"46": ""}]}